CHANGELOG.txt
LICENSE.txt
MANIFEST.in
README.txt
setup.cfg
setup.py
NestedRecord.egg-info/PKG-INFO
NestedRecord.egg-info/SOURCES.txt
NestedRecord.egg-info/dependency_links.txt
NestedRecord.egg-info/entry_points.txt
NestedRecord.egg-info/not-zip-safe
NestedRecord.egg-info/requires.txt
NestedRecord.egg-info/top_level.txt
doc/index.txt
doc/source/conf.py
doc/source/index.rst
doc/source/manual.rst
nestedrecord/__init__.py
nestedrecord/internal.py
test/README.txt
test/doc.py