Metadata-Version: 1.0
Name: NestedRecord
Version: 0.3.0
Summary: Tools for handling the NestedRecord encoding, a useful way of representing nested structures of dictionaries and lists as flat key-value pairs by using a convention for key names.
Home-page: http://jimmyg.org/work/code/nestedrecord/index.html
Author: James Gardner
Author-email: UNKNOWN
License: GNU AGPLv3
Platform: UNKNOWN
